[
  {
    "ID": "BT-1",
    "Business Term": "Invoice number",
    "Type of Change": "none"
  },
  {
    "ID": "BT-2",
    "Business Term": "Invoice issue date",
    "Type of Change": "none"
  },
  {
    "ID": "BT-3",
    "Business Term": "Invoice type code",
    "Type of Change": "none"
  },
  {
    "ID": "BT-5",
    "Business Term": "Invoice currency code",
    "Type of Change": "none"
  },
  {
    "ID": "BG-2",
    "Business Term": "PROCESS CONTROL",
    "Type of Change": "none"
  },
  {
    "ID": "BT-24",
    "Business Term": "Specification identifier",
    "Type of Change": "none"
  },
  {
    "ID": "BG-4",
    "Business Term": "SELLER",
    "Type of Change": "none"
  },
  {
    "ID": "BT-27",
    "Business Term": "Seller name",
    "Type of Change": "none"
  },
  {
    "ID": "BG-5",
    "Business Term": "SELLER POSTAL ADDRESS",
    "Type of Change": "none"
  },
  {
    "ID": "BT-40",
    "Business Term": "Seller country code",
    "Type of Change": "none"
  },
  {
    "ID": "BG-7",
    "Business Term": "BUYER",
    "Type of Change": "none"
  },
  {
    "ID": "BT-44",
    "Business Term": "Buyer name",
    "Type of Change": "none"
  },
  {
    "ID": "BG-8",
    "Business Term": "BUYER POSTAL ADDRESS",
    "Type of Change": "none"
  },
  {
    "ID": "BT-55",
    "Business Term": "Buyer country code",
    "Type of Change": "none"
  },
  {
    "ID": "BG-22",
    "Business Term": "DOCUMENT TOTALS",
    "Type of Change": "none"
  },
  {
    "ID": "BT-106",
    "Business Term": "Sum of invoice line net amount",
    "Type of Change": "none"
  },
  {
    "ID": "BT-109",
    "Business Term": "Invoice total amount without VAT",
    "Type of Change": "none"
  },
  {
    "ID": "BT-112",
    "Business Term": "Invoice total amount with VAT",
    "Type of Change": "none"
  },
  {
    "ID": "BG-23",
    "Business Term": "VAT BREAKDOWN",
    "Type of Change": "none"
  },
  {
    "ID": "BT-164",
    "Business Term": "VAT breakdown currency",
    "Type of Change": "none"
  },
  {
    "ID": "BT-116",
    "Business Term": "VAT category taxable amount",
    "Type of Change": "none"
  },
  {
    "ID": "BT-117",
    "Business Term": "VAT category tax amount",
    "Type of Change": "none"
  },
  {
    "ID": "BT-118",
    "Business Term": "VAT category code",
    "Type of Change": "none"
  },
  {
    "ID": "BG-25",
    "Business Term": "INVOICE LINE",
    "Type of Change": "none"
  },
  {
    "ID": "BT-126",
    "Business Term": "Invoice line identifier",
    "Type of Change": "none"
  },
  {
    "ID": "BT-129",
    "Business Term": "Invoiced quantity",
    "Type of Change": "none"
  },
  {
    "ID": "BT-130",
    "Business Term": "Invoiced quantity unit of measure code",
    "Type of Change": "none"
  },
  {
    "ID": "BT-131",
    "Business Term": "Invoice line net amount",
    "Type of Change": "none"
  },
  {
    "ID": "BG-29",
    "Business Term": "PRICE DETAILS",
    "Type of Change": "none"
  },
  {
    "ID": "BT-146",
    "Business Term": "Item net price",
    "Type of Change": "none"
  },
  {
    "ID": "BG-30",
    "Business Term": "LINE VAT INFORMATION",
    "Type of Change": "none"
  },
  {
    "ID": "BT-151",
    "Business Term": "Invoiced item VAT category code",
    "Type of Change": "none"
  },
  {
    "ID": "BG-31",
    "Business Term": "ITEM INFORMATION",
    "Type of Change": "none"
  },
  {
    "ID": "BT-153",
    "Business Term": "Item name",
    "Type of Change": "none"
  }
]
